data_pipeline_api/__init__.py
data_pipeline_api/ext/SEIRSModelRun.py
data_pipeline_api/ext/SEIRSconfig.yaml
data_pipeline_api/ext/SEIRSconfigWindows.yaml
data_pipeline_api/ext/__init__.py
data_pipeline_api/ext/static_params_SEIRS.csv
data_pipeline_api/fdp_utils.py
data_pipeline_api/link.py
data_pipeline_api/pipeline.py
data_pipeline_api/raise_issue.py
data_pipeline_api-0.9.0.dist-info/LICENSE
data_pipeline_api-0.9.0.dist-info/METADATA
data_pipeline_api-0.9.0.dist-info/WHEEL
data_pipeline_api-0.9.0.dist-info/RECORD
