Metadata-Version: 2.1
Name: data_pipeline_api
Version: 0.9.0
Summary: Python api to interact with the Fair Data Pipeline
Home-page: https://www.fairdatapipeline.org/
License: GNU General Public License v3.0
Keywords: FAIR Data Pipeline,FAIR,Data Management,Provenance
Author: Ryan J Field
Author-email: ryan.field@glasgow.ac.uk
Requires-Python: >=3.9,<4.0
Classifier: License :: Other/Proprietary License
Classifier: Programming Language :: Python :: 3
Classifier: Programming Language :: Python :: 3.9
Classifier: Programming Language :: Python :: 3.10
Classifier: Programming Language :: Python :: 3.11
Classifier: Programming Language :: Python :: 3.12
Classifier: Programming Language :: Python :: 3.13
Requires-Dist: PyYAML (>=6.0,<7.0)
Requires-Dist: requests (>=2.23.0,<3.0.0)
Project-URL: Issue Tracker, https://github.com/FAIRDataPipeline/pyDataPipeline/issues
Project-URL: Repository, https://github.com/FAIRDataPipeline/pyDataPipeline
